README.rst
setup.py
django_rest_tools/__init__.py
django_rest_tools/fields.py
django_rest_tools/filters.py
django_rest_tools.egg-info/PKG-INFO
django_rest_tools.egg-info/SOURCES.txt
django_rest_tools.egg-info/dependency_links.txt
django_rest_tools.egg-info/requires.txt
django_rest_tools.egg-info/top_level.txt