Metadata-Version: 1.1
Name: django-rest-tools
Version: 1.1
Summary: Tools for Django Rest Framework
Home-page: https://github.com/quiqueporta/django-rest-tools
Author: Quique Porta
Author-email: quiqueporta@gmail.com
License: GPLv3
Download-URL: https://github.com/quiqueporta/django-rest-tools/releases
Keywords: django,djangorestframework,tools
Platform: UNKNOWN
Classifier: Development Status :: 5 - Production/Stable
Classifier: Environment :: Web Environment
Classifier: Framework :: Django
Classifier: Intended Audience :: Developers
Classifier: License :: OSI Approved :: GNU Lesser General Public License v3 (LGPLv3)
Classifier: Natural Language :: English
Classifier: Operating System :: OS Independent
Classifier: Programming Language :: Python
Classifier: Topic :: Internet :: WWW/HTTP
